{
  "version": "7",
  "dialect": "postgresql",
  "entries": [
    {
      "idx": 0,
      "version": "7",
      "when": 1770558614183,
      "tag": "0000_numerous_sue_storm",
      "breakpoints": true
    },
    {
      "idx": 1,
      "version": "7",
      "when": 1771364745409,
      "tag": "0001_aspiring_kree",
      "breakpoints": true
    },
    {
      "idx": 2,
      "version": "7",
      "when": 1771679851502,
      "tag": "0002_slow_lady_mastermind",
      "breakpoints": true
    },
    {
      "idx": 3,
      "version": "7",
      "when": 1771695009957,
      "tag": "0003_silent_shard",
      "breakpoints": true
    }
  ]
}
